openCleanlib/WranglingAndCleaning.py
openCleanlib/__init__.py
openCleanlib/profiling.py
openCleanlib/transformation.py
openCleanlib/utils.py
openCleanlib-0.1.0.dist-info/METADATA
openCleanlib-0.1.0.dist-info/WHEEL
openCleanlib-0.1.0.dist-info/top_level.txt
openCleanlib-0.1.0.dist-info/RECORD
