Metadata-Version: 2.1
Name: openCleanlib
Version: 0.1.0
Summary: Uma biblioteca para limpeza, transformação e wrangling de dados usando OpenClean
Home-page: https://github.com/...
Author: Andrei Portugal,... 
Author-email: andrei.torres@aluno.uece.br,...
Classifier: Programming Language :: Python :: 3
Classifier: License :: OSI Approved :: MIT License
Classifier: Operating System :: OS Independent
Requires-Python: >=3.6
Requires-Dist: openclean
Requires-Dist: pandas
